unittest_xml_reporting-3.2.0.data/data/LICENSE
xmlrunner/__init__.py
xmlrunner/__main__.py
xmlrunner/builder.py
xmlrunner/result.py
xmlrunner/runner.py
xmlrunner/unittest.py
xmlrunner/version.py
xmlrunner/extra/__init__.py
xmlrunner/extra/djangotestrunner.py
xmlrunner/extra/xunit_plugin.py
unittest_xml_reporting-3.2.0.dist-info/LICENSE
unittest_xml_reporting-3.2.0.dist-info/METADATA
unittest_xml_reporting-3.2.0.dist-info/WHEEL
unittest_xml_reporting-3.2.0.dist-info/top_level.txt
unittest_xml_reporting-3.2.0.dist-info/RECORD
