Metadata-Version: 2.1
Name: unittest-xml-reporting
Version: 3.2.0
Summary: unittest-based test runner with Ant/JUnit like XML reporting.
Home-page: http://github.com/xmlrunner/unittest-xml-reporting/tree/master/
Author: Daniel Fernandes Martins, Damien Nozay
License: BSD
Keywords: pyunit,unittest,junit xml,xunit,report,testrunner,xmlrunner
Platform: Any
Classifier: Development Status :: 5 - Production/Stable
Classifier: Intended Audience :: Developers
Classifier: License :: OSI Approved :: BSD License
Classifier: Natural Language :: English
Classifier: Operating System :: OS Independent
Classifier: Programming Language :: Python
Classifier: Programming Language :: Python :: 3
Classifier: Programming Language :: Python :: 3 :: Only
Classifier: Programming Language :: Python :: 3.7
Classifier: Programming Language :: Python :: 3.8
Classifier: Programming Language :: Python :: 3.9
Classifier: Programming Language :: Python :: 3.10
Classifier: Programming Language :: Python :: Implementation :: CPython
Classifier: Programming Language :: Python :: Implementation :: PyPy
Classifier: Topic :: Software Development :: Libraries :: Python Modules
Classifier: Topic :: Software Development :: Testing
Requires-Python: >=3.7
License-File: LICENSE
